{
  "prefixes": [
    "autospurgo",
    "frantoio-mobile-inerti",
    "noleggio-bagni-chimici",
    "pulizia-fognature",
    "spurgo-fosse-biologiche",
    "trasporto-acqua",
    "trasporto-rifiuti"
  ],
  "suffixes": [
    { "path": "agrigento", "title": "Agrigento" },
    { "path": "alessandria", "title": "Alessandria" },
    { "path": "ancona", "title": "Ancona" },
    { "path": "arezzo", "title": "Arezzo" },
    { "path": "ascoli-piceno", "title": "Ascoli Piceno" },
    { "path": "asti", "title": "Asti" },
    { "path": "avellino", "title": "Avellino" },
    { "path": "bari", "title": "Bari" },
    { "path": "barletta-andria-trani", "title": "Barletta-Andria-Trani" },
    { "path": "belluno", "title": "Belluno" },
    { "path": "benevento", "title": "Benevento" },
    { "path": "bergamo", "title": "Bergamo" },
    { "path": "biella", "title": "Biella" },
    { "path": "bologna", "title": "Bologna" },
    { "path": "bolzano", "title": "Bolzano" },
    { "path": "brescia", "title": "Brescia" },
    { "path": "brindisi", "title": "Brindisi" },
    { "path": "cagliari", "title": "Cagliari" },
    { "path": "caltanissetta", "title": "Caltanissetta" },
    { "path": "campobasso", "title": "Campobasso" },
    { "path": "carbonia-iglesias", "title": "Carbonia Iglesias" },
    { "path": "caserta", "title": "Caserta" },
    { "path": "catania", "title": "Catania" },
    { "path": "catanzaro", "title": "Catanzaro" },
    { "path": "chieti", "title": "Chieti" },
    { "path": "como", "title": "Como" },
    { "path": "cosenza", "title": "Cosenza" },
    { "path": "cremona", "title": "Cremona" },
    { "path": "crotone", "title": "Crotone" },
    { "path": "cuneo", "title": "Cuneo" },
    { "path": "enna", "title": "Enna" },
    { "path": "fermo", "title": "Fermo" },
    { "path": "ferrara", "title": "Ferrara" },
    { "path": "firenze", "title": "Firenze" },
    { "path": "foggia", "title": "Foggia" },
    { "path": "forli-cesena", "title": "Forlì-Cesena" },
    { "path": "frosinone", "title": "Frosinone" },
    { "path": "genova", "title": "Genova" },
    { "path": "gorizia", "title": "Gorizia" },
    { "path": "grosseto", "title": "Grosseto" },
    { "path": "imperia", "title": "Imperia" },
    { "path": "isernia", "title": "Isernia" },
    { "path": "l-aquila", "title": "L'Aquila" },
    { "path": "la-spezia", "title": "La Spezia" },
    { "path": "latina", "title": "Latina" },
    { "path": "lecce", "title": "Lecce" },
    { "path": "lecco", "title": "Lecco" },
    { "path": "livorno", "title": "Livorno" },
    { "path": "lodi", "title": "Lodi" },
    { "path": "lucca", "title": "Lucca" },
    { "path": "macerata", "title": "Macerata" },
    { "path": "mantova", "title": "Mantova" },
    { "path": "massa-carrara", "title": "Massa-Carrara" },
    { "path": "matera", "title": "Matera" },
    { "path": "medio-campidano", "title": "Medio Campidano" },
    { "path": "messina", "title": "Messina" },
    { "path": "milano", "title": "Milano" },
    { "path": "modena", "title": "Modena" },
    { "path": "monza-brianza", "title": "Monza Brianza" },
    { "path": "napoli", "title": "Napoli" },
    { "path": "novara", "title": "Novara" },
    { "path": "nuoro", "title": "Nuoro" },
    { "path": "ogliastra", "title": "Ogliastra" },
    { "path": "olbia-tempio", "title": "Olbia-Tempio" },
    { "path": "oristano", "title": "Oristano" },
    { "path": "padova", "title": "Padova" },
    { "path": "palermo", "title": "Palermo" },
    { "path": "parma", "title": "Parma" },
    { "path": "pavia", "title": "Pavia" },
    { "path": "perugia", "title": "Perugia" },
    { "path": "pesaro-urbino", "title": "Pesaro-Urbino" },
    { "path": "pescara", "title": "Pescara" },
    { "path": "piacenza", "title": "Piacenza" },
    { "path": "pisa", "title": "Pisa" },
    { "path": "pistoia", "title": "Pistoia" },
    { "path": "pordenone", "title": "Pordenone" },
    { "path": "potenza", "title": "Potenza" },
    { "path": "prato", "title": "Prato" },
    { "path": "ragusa", "title": "Ragusa" },
    { "path": "ravenna", "title": "Ravenna" },
    { "path": "reggio-calabria", "title": "Reggio Calabria" },
    { "path": "reggio-emilia", "title": "Reggio Emilia" },
    { "path": "rieti", "title": "Rieti" },
    { "path": "rimini", "title": "Rimini" },
    { "path": "roma", "title": "Roma" },
    { "path": "rovigo", "title": "Rovigo" },
    { "path": "salerno", "title": "Salerno" },
    { "path": "sassari", "title": "Sassari" },
    { "path": "savona", "title": "Savona" },
    { "path": "siena", "title": "Siena" },
    { "path": "siracusa", "title": "Siracusa" },
    { "path": "sondrio", "title": "Sondrio" },
    { "path": "taranto", "title": "Taranto" },
    { "path": "teramo", "title": "Teramo" },
    { "path": "terni", "title": "Terni" },
    { "path": "torino", "title": "Torino" },
    { "path": "trapani", "title": "Trapani" },
    { "path": "trento", "title": "Trento" },
    { "path": "treviso", "title": "Treviso" },
    { "path": "trieste", "title": "Trieste" },
    { "path": "udine", "title": "Udine" },
    { "path": "varese", "title": "Varese" },
    { "path": "venezia", "title": "Venezia" },
    { "path": "verbano-cusio-ossola", "title": "Verbano-Cusio-Ossola" },
    { "path": "vercelli", "title": "Vercelli" },
    { "path": "verona", "title": "Verona" },
    { "path": "vibo-valentia", "title": "Vibo Valentia" },
    { "path": "vicenza", "title": "Vicenza" },
    { "path": "viterbo", "title": "Viterbo" },

    { "path": "anghiari", "title": "Anghiari", "province": {"label": "Arezzo", "path": "arezzo"} },
    {
      "path": "badia-prataglia",
      "title": "Badia Prataglia",
      "province": {"label": "Arezzo", "path": "arezzo"}
    },
    { "path": "badia-tedalda", "title": "Badia Tedalda", "province": {"label": "Arezzo", "path": "arezzo"} },
    { "path": "bibbiena", "title": "Bibbiena", "province": {"label": "Arezzo", "path": "arezzo"} },
    { "path": "bucine", "title": "Bucine", "province": {"label": "Arezzo", "path": "arezzo"} },
    { "path": "camucia", "title": "Camucia", "province": {"label": "Arezzo", "path": "arezzo"} },
    { "path": "capolona", "title": "Capolona", "province": {"label": "Arezzo", "path": "arezzo"} },
    {
      "path": "caprese-michelangelo",
      "title": "Caprese Michelangelo",
      "province": {"label": "Arezzo", "path": "arezzo"}
    },
    {
      "path": "castel-focognano",
      "title": "Castel Focognano",
      "province": {"label": "Arezzo", "path": "arezzo"}
    },
    {
      "path": "castel-san-niccolo",
      "title": "Castel San Niccolò",
      "province": {"label": "Arezzo", "path": "arezzo"}
    },
    {
      "path": "castelfranco-piandisco",
      "title": "Castelfranco Piandiscò",
      "province": {"label": "Arezzo", "path": "arezzo"}
    },
    {
      "path": "castiglion-fibocchi",
      "title": "Castiglion Fibocchi",
      "province": {"label": "Arezzo", "path": "arezzo"}
    },
    {
      "path": "castiglion-fiorentino",
      "title": "Castiglion Fiorentino",
      "province": {"label": "Arezzo", "path": "arezzo"}
    },
    { "path": "cavriglia", "title": "Cavriglia", "province": {"label": "Arezzo", "path": "arezzo"} },
    {
      "path": "cesa-in-valdichiana",
      "title": "Cesa in valdichiana",
      "province": {"label": "Arezzo", "path": "arezzo"}
    },
    { "path": "chitignano", "title": "Chitignano", "province": {"label": "Arezzo", "path": "arezzo"} },
    {
      "path": "chiusi-della-verna",
      "title": "Chiusi della Verna",
      "province": {"label": "Arezzo", "path": "arezzo"}
    },
    {
      "path": "civitella-in-valdichiana",
      "title": "Civitella in Valdichiana",
      "province": {"label": "Arezzo", "path": "arezzo"}
    },
    { "path": "cortona", "title": "Cortona", "province": {"label": "Arezzo", "path": "arezzo"} },
    {
      "path": "figline-valdarno",
      "title": "Figline Valdarno",
      "province": {"label": "Arezzo", "path": "arezzo"}
    },
    {
      "path": "foiano-in-valdichiana",
      "title": "Foiano in Valdichiana",
      "province": {"label": "Arezzo", "path": "arezzo"}
    },
    { "path": "laterina", "title": "Laterina", "province": {"label": "Arezzo", "path": "arezzo"} },
    {
      "path": "loro-ciuffenna",
      "title": "Loro ciuffenna",
      "province": {"label": "Arezzo", "path": "arezzo"}
    },
    { "path": "lucignano", "title": "Lucignano", "province": {"label": "Arezzo", "path": "arezzo"} },
    {
      "path": "marciano-della-chiana",
      "title": "Marciano della Chiana",
      "province": {"label": "Arezzo", "path": "arezzo"}
    },
    {
      "path": "monte-san-savino",
      "title": "Monte San Savino",
      "province": {"label": "Arezzo", "path": "arezzo"}
    },
    { "path": "montemignaio", "title": "Montemignaio", "province": {"label": "Arezzo", "path": "arezzo"} },
    { "path": "monterchi", "title": "Monterchi", "province": {"label": "Arezzo", "path": "arezzo"} },
    { "path": "montevarchi", "title": "Montevarchi", "province": {"label": "Arezzo", "path": "arezzo"} },
    {
      "path": "ortignano-raggiolo",
      "title": "Ortignano Raggiolo",
      "province": {"label": "Arezzo", "path": "arezzo"}
    },
    {
      "path": "pergine-valdarno",
      "title": "Pergine Valdarno",
      "province": {"label": "Arezzo", "path": "arezzo"}
    },
    {
      "path": "pieve-al-toppo",
      "title": "Pieve al Toppo",
      "province": {"label": "Arezzo", "path": "arezzo"}
    },
    {
      "path": "pieve-santo-stefano",
      "title": "Pieve Santo Stefano",
      "province": {"label": "Arezzo", "path": "arezzo"}
    },
    { "path": "poppi", "title": "Poppi", "province": {"label": "Arezzo", "path": "arezzo"} },
    {
      "path": "pratovecchio-stia",
      "title": "Pratovecchio Stia",
      "province": {"label": "Arezzo", "path": "arezzo"}
    },
    { "path": "rassina", "title": "Rassina", "province": {"label": "Arezzo", "path": "arezzo"} },
    { "path": "rigutino", "title": "Rigutino", "province": {"label": "Arezzo", "path": "arezzo"} },
    {
      "path": "san-giovanni-valdarno",
      "title": "San Giovanni Valdarno",
      "province": {"label": "Arezzo", "path": "arezzo"}
    },
    { "path": "sansepolcro", "title": "Sansepolcro", "province": {"label": "Arezzo", "path": "arezzo"} },
    { "path": "sestino", "title": "Sestino", "province": {"label": "Arezzo", "path": "arezzo"} },
    { "path": "soci", "title": "Soci", "province": {"label": "Arezzo", "path": "arezzo"} },
    { "path": "subbiano", "title": "Subbiano", "province": {"label": "Arezzo", "path": "arezzo"} },
    { "path": "talla", "title": "Talla", "province": {"label": "Arezzo", "path": "arezzo"} },
    {
      "path": "terranuova-bracciolini",
      "title": "Terranuova Bracciolini",
      "province": {"label": "Arezzo", "path": "arezzo"}
    },

    {
      "path": "bagno-a-ripoli",
      "title": "Bagno a Ripoli",
      "province": {"label": "Firenze", "path": "firenze"}
    },
    {
      "path": "barberino-di-mugello",
      "title": "Barberino di Mugello",
      "province": {"label": "Firenze", "path": "firenze"}
    },
    {
      "path": "barberino-tavarnelle",
      "title": "Barberino Tavarnelle",
      "province": {"label": "Firenze", "path": "firenze"}
    },
    {
      "path": "borgo-san-lorenzo",
      "title": "Borgo San Lorenzo",
      "province": {"label": "Firenze", "path": "firenze"}
    },
    { "path": "calenzano", "title": "Calenzano", "province": {"label": "Firenze", "path": "firenze"} },
    {
      "path": "campi-bisenzio",
      "title": "Campi Bisenzio",
      "province": {"label": "Firenze", "path": "firenze"}
    },
    {
      "path": "capraia-e-limite",
      "title": "Capraia e Limite",
      "province": {"label": "Firenze", "path": "firenze"}
    },
    {
      "path": "castelfiorentino",
      "title": "Castelfiorentino",
      "province": {"label": "Firenze", "path": "firenze"}
    },
    {
      "path": "cerreto-guidi",
      "title": "Cerreto Guidi",
      "province": {"label": "Firenze", "path": "firenze"}
    },
    { "path": "certaldo", "title": "Certaldo", "province": {"label": "Firenze", "path": "firenze"} },
    { "path": "dicomano", "title": "Dicomano", "province": {"label": "Firenze", "path": "firenze"} },
    { "path": "empoli", "title": "Empoli", "province": {"label": "Firenze", "path": "firenze"} },
    { "path": "fiesole", "title": "Fiesole", "province": {"label": "Firenze", "path": "firenze"} },
    {
      "path": "figline-e-incisa-valdarno",
      "title": "Figline e Incisa Valdarno",
      "province": {"label": "Firenze", "path": "firenze"}
    },
    { "path": "firenze", "title": "Firenze", "province": {"label": "Firenze", "path": "firenze"} },
    { "path": "firenzuola", "title": "Firenzuola", "province": {"label": "Firenze", "path": "firenze"} },
    { "path": "fucecchio", "title": "Fucecchio", "province": {"label": "Firenze", "path": "firenze"} },
    {
      "path": "gambassi-terme",
      "title": "Gambassi Terme",
      "province": {"label": "Firenze", "path": "firenze"}
    },
    {
      "path": "greve-in-chianti",
      "title": "Greve in Chianti",
      "province": {"label": "Firenze", "path": "firenze"}
    },
    { "path": "impruneta", "title": "Impruneta", "province": {"label": "Firenze", "path": "firenze"} },
    {
      "path": "lastra-a-signa",
      "title": "Lastra a Signa",
      "province": {"label": "Firenze", "path": "firenze"}
    },
    { "path": "londa", "title": "Londa", "province": {"label": "Firenze", "path": "firenze"} },
    { "path": "marradi", "title": "Marradi", "province": {"label": "Firenze", "path": "firenze"} },
    { "path": "montaione", "title": "Montaione", "province": {"label": "Firenze", "path": "firenze"} },
    {
      "path": "montelupo-fiorentino",
      "title": "Montelupo Fiorentino",
      "province": {"label": "Firenze", "path": "firenze"}
    },
    {
      "path": "montespertoli",
      "title": "Montespertoli",
      "province": {"label": "Firenze", "path": "firenze"}
    },
    {
      "path": "palazzuolo-sul-senio",
      "title": "Palazzuolo sul Senio",
      "province": {"label": "Firenze", "path": "firenze"}
    },
    { "path": "pelago", "title": "Pelago", "province": {"label": "Firenze", "path": "firenze"} },
    { "path": "pontassieve", "title": "Pontassieve", "province": {"label": "Firenze", "path": "firenze"} },
    { "path": "reggello", "title": "Reggello", "province": {"label": "Firenze", "path": "firenze"} },
    {
      "path": "rignano-sull-arno",
      "title": "Rignano sull'Arno",
      "province": {"label": "Firenze", "path": "firenze"}
    },
    { "path": "rufina", "title": "Rufina", "province": {"label": "Firenze", "path": "firenze"} },
    {
      "path": "san-casciano-in-val-di-pesa",
      "title": "San Casciano in Val di Pesa",
      "province": {"label": "Firenze", "path": "firenze"}
    },
    { "path": "san-godenzo", "title": "San Godenzo", "province": {"label": "Firenze", "path": "firenze"} },
    { "path": "scandicci", "title": "Scandicci", "province": {"label": "Firenze", "path": "firenze"} },
    {
      "path": "scarperia-e-san-piero",
      "title": "Scarperia e San Piero",
      "province": {"label": "Firenze", "path": "firenze"}
    },
    {
      "path": "sesto-fiorentino",
      "title": "Sesto Fiorentino",
      "province": {"label": "Firenze", "path": "firenze"}
    },
    { "path": "signa", "title": "Signa", "province": {"label": "Firenze", "path": "firenze"} },
    { "path": "vaglia", "title": "Vaglia", "province": {"label": "Firenze", "path": "firenze"} },
    { "path": "vicchio", "title": "Vicchio", "province": {"label": "Firenze", "path": "firenze"} },
    { "path": "vinci", "title": "Vinci", "province": {"label": "Firenze", "path": "firenze"} },

    { "path": "assisi", "title": "Assisi", "province": {"label": "Perugia", "path": "perugia"} },
    { "path": "bastia-umbra", "title": "Bastia Umbra", "province": {"label": "Perugia", "path": "perugia"} },
    { "path": "bettona", "title": "Bettona", "province": {"label": "Perugia", "path": "perugia"} },
    { "path": "bevagna", "title": "Bevagna", "province": {"label": "Perugia", "path": "perugia"} },
    {
      "path": "campello-sul-clitunno",
      "title": "Campello sul Clitunno",
      "province": {"label": "Perugia", "path": "perugia"}
    },
    { "path": "cannara", "title": "Cannara", "province": {"label": "Perugia", "path": "perugia"} },
    { "path": "cascia", "title": "Cascia", "province": {"label": "Perugia", "path": "perugia"} },
    {
      "path": "castel-ritaldi",
      "title": "Castel Ritaldi",
      "province": {"label": "Perugia", "path": "perugia"}
    },
    {
      "path": "castiglione-del-lago",
      "title": "Castiglione del Lago",
      "province": {"label": "Perugia", "path": "perugia"}
    },
    {
      "path": "cerreto-di-spoleto",
      "title": "Cerreto di Spoleto",
      "province": {"label": "Perugia", "path": "perugia"}
    },
    { "path": "citerna", "title": "Citerna", "province": {"label": "Perugia", "path": "perugia"} },
    {
      "path": "citta-della-pieve",
      "title": "Città della Pieve",
      "province": {"label": "Perugia", "path": "perugia"}
    },
    {
      "path": "citta-di-castello",
      "title": "Città di Castello",
      "province": {"label": "Perugia", "path": "perugia"}
    },
    { "path": "collazzone", "title": "Collazzone", "province": {"label": "Perugia", "path": "perugia"} },
    { "path": "corciano", "title": "Corciano", "province": {"label": "Perugia", "path": "perugia"} },
    { "path": "costacciaro", "title": "Costacciaro", "province": {"label": "Perugia", "path": "perugia"} },
    { "path": "deruta", "title": "Deruta", "province": {"label": "Perugia", "path": "perugia"} },
    { "path": "foligno", "title": "Foligno", "province": {"label": "Perugia", "path": "perugia"} },
    {
      "path": "fossato-di-vico",
      "title": "Fossato di Vico",
      "province": {"label": "Perugia", "path": "perugia"}
    },
    {
      "path": "fratta-todina",
      "title": "Fratta Todina",
      "province": {"label": "Perugia", "path": "perugia"}
    },
    {
      "path": "giano-dell-umbria",
      "title": "Giano dell'Umbria",
      "province": {"label": "Perugia", "path": "perugia"}
    },
    {
      "path": "gualdo-cattaneo",
      "title": "Gualdo Cattaneo",
      "province": {"label": "Perugia", "path": "perugia"}
    },
    {
      "path": "gualdo-tadino",
      "title": "Gualdo Tadino",
      "province": {"label": "Perugia", "path": "perugia"}
    },
    { "path": "gubbio", "title": "Gubbio", "province": {"label": "Perugia", "path": "perugia"} },
    {
      "path": "lisciano-niccone",
      "title": "Lisciano Niccone",
      "province": {"label": "Perugia", "path": "perugia"}
    },
    { "path": "magione", "title": "Magione", "province": {"label": "Perugia", "path": "perugia"} },
    { "path": "marsciano", "title": "Marsciano", "province": {"label": "Perugia", "path": "perugia"} },
    {
      "path": "massa-martana",
      "title": "Massa Martana",
      "province": {"label": "Perugia", "path": "perugia"}
    },
    {
      "path": "monte-castello-di-vibio",
      "title": "Monte Castello di Vibio",
      "province": {"label": "Perugia", "path": "perugia"}
    },
    {
      "path": "monte-santa-maria-tiberina",
      "title": "Monte Santa Maria Tiberina",
      "province": {"label": "Perugia", "path": "perugia"}
    },
    { "path": "montefalco", "title": "Montefalco", "province": {"label": "Perugia", "path": "perugia"} },
    {
      "path": "monteleone-di-spoleto",
      "title": "Monteleone di Spoleto",
      "province": {"label": "Perugia", "path": "perugia"}
    },
    { "path": "montone", "title": "Montone", "province": {"label": "Perugia", "path": "perugia"} },
    { "path": "nocera-umbra", "title": "Nocera Umbra", "province": {"label": "Perugia", "path": "perugia"} },
    { "path": "norcia", "title": "Norcia", "province": {"label": "Perugia", "path": "perugia"} },
    { "path": "paciano", "title": "Paciano", "province": {"label": "Perugia", "path": "perugia"} },
    { "path": "panicale", "title": "Panicale", "province": {"label": "Perugia", "path": "perugia"} },
    {
      "path": "passignano-sul-trasimeno",
      "title": "Passignano sul Trasimeno",
      "province": {"label": "Perugia", "path": "perugia"}
    },
    { "path": "perugia", "title": "Perugia", "province": {"label": "Perugia", "path": "perugia"} },
    { "path": "piegaro", "title": "Piegaro", "province": {"label": "Perugia", "path": "perugia"} },
    { "path": "pietralunga", "title": "Pietralunga", "province": {"label": "Perugia", "path": "perugia"} },
    { "path": "poggiodomo", "title": "Poggiodomo", "province": {"label": "Perugia", "path": "perugia"} },
    { "path": "preci", "title": "Preci", "province": {"label": "Perugia", "path": "perugia"} },
    { "path": "san-giustino", "title": "San Giustino", "province": {"label": "Perugia", "path": "perugia"} },
    {
      "path": "sant-anatolia-di-narco",
      "title": "Sant'Anatolia di Narco",
      "province": {"label": "Perugia", "path": "perugia"}
    },
    {
      "path": "scheggia-e-pascelupo",
      "title": "Scheggia e Pascelupo",
      "province": {"label": "Perugia", "path": "perugia"}
    },
    { "path": "scheggino", "title": "Scheggino", "province": {"label": "Perugia", "path": "perugia"} },
    { "path": "sellano", "title": "Sellano", "province": {"label": "Perugia", "path": "perugia"} },
    { "path": "sigillo", "title": "Sigillo", "province": {"label": "Perugia", "path": "perugia"} },
    { "path": "spello", "title": "Spello", "province": {"label": "Perugia", "path": "perugia"} },
    { "path": "spoleto", "title": "Spoleto", "province": {"label": "Perugia", "path": "perugia"} },
    { "path": "todi", "title": "Todi", "province": {"label": "Perugia", "path": "perugia"} },
    { "path": "torgiano", "title": "Torgiano", "province": {"label": "Perugia", "path": "perugia"} },
    { "path": "trevi", "title": "Trevi", "province": {"label": "Perugia", "path": "perugia"} },
    {
      "path": "tuoro-sul-trasimeno",
      "title": "Tuoro sul Trasimeno",
      "province": {"label": "Perugia", "path": "perugia"}
    },
    { "path": "umbertide", "title": "Umbertide", "province": {"label": "Perugia", "path": "perugia"} },
    { "path": "valfabbrica", "title": "Valfabbrica", "province": {"label": "Perugia", "path": "perugia"} },
    {
      "path": "vallo-di-nera",
      "title": "Vallo di Nera",
      "province": {"label": "Perugia", "path": "perugia"}
    },
    { "path": "valtopina", "title": "Valtopina", "province": {"label": "Perugia", "path": "perugia"} },

    {
      "path": "bagno-di-romagna",
      "title": "Bagno di Romagna",
      "province": {"label": "Forlì Cesena", "path": "forli-cesena"}
    },
    { "path": "bertinoro", "title": "Bertinoro", "province": {"label": "Forlì Cesena", "path": "forli-cesena"} },
    { "path": "borghi", "title": "Borghi", "province": {"label": "Forlì Cesena", "path": "forli-cesena"} },
    {
      "path": "castrocaro-terme-e-terra-del-sole",
      "title": "Castrocaro Terme e Terra del Sole",
      "province": {"label": "Forlì Cesena", "path": "forli-cesena"}
    },
    { "path": "cesena", "title": "Cesena", "province": {"label": "Forlì Cesena", "path": "forli-cesena"} },
    { "path": "cesenatico", "title": "Cesenatico", "province": {"label": "Forlì Cesena", "path": "forli-cesena"} },
    {
      "path": "civitella-di-romagna",
      "title": "Civitella di Romagna",
      "province": {"label": "Forlì Cesena", "path": "forli-cesena"}
    },
    { "path": "dovadola", "title": "Dovadola", "province": {"label": "Forlì Cesena", "path": "forli-cesena"} },
    { "path": "forli", "title": "Forlì", "province": {"label": "Forlì Cesena", "path": "forli-cesena"} },
    {
      "path": "forlimpopoli",
      "title": "Forlimpopoli",
      "province": {"label": "Forlì Cesena", "path": "forli-cesena"}
    },
    { "path": "galeata", "title": "Galeata", "province": {"label": "Forlì Cesena", "path": "forli-cesena"} },
    { "path": "gambettola", "title": "Gambettola", "province": {"label": "Forlì Cesena", "path": "forli-cesena"} },
    { "path": "gatteo", "title": "Gatteo", "province": {"label": "Forlì Cesena", "path": "forli-cesena"} },
    { "path": "longiano", "title": "Longiano", "province": {"label": "Forlì Cesena", "path": "forli-cesena"} },
    { "path": "meldola", "title": "Meldola", "province": {"label": "Forlì Cesena", "path": "forli-cesena"} },
    {
      "path": "mercato-saraceno",
      "title": "Mercato Saraceno",
      "province": {"label": "Forlì Cesena", "path": "forli-cesena"}
    },
    { "path": "modigliana", "title": "Modigliana", "province": {"label": "Forlì Cesena", "path": "forli-cesena"} },
    { "path": "montiano", "title": "Montiano", "province": {"label": "Forlì Cesena", "path": "forli-cesena"} },
    {
      "path": "portico-e-san-benedetto",
      "title": "Portico e San Benedetto",
      "province": {"label": "Forlì Cesena", "path": "forli-cesena"}
    },
    { "path": "predappio", "title": "Predappio", "province": {"label": "Forlì Cesena", "path": "forli-cesena"} },
    {
      "path": "premilcuore",
      "title": "Premilcuore",
      "province": {"label": "Forlì Cesena", "path": "forli-cesena"}
    },
    {
      "path": "rocca-san-casciano",
      "title": "Rocca San Casciano",
      "province": {"label": "Forlì Cesena", "path": "forli-cesena"}
    },
    {
      "path": "roncofreddo",
      "title": "Roncofreddo",
      "province": {"label": "Forlì Cesena", "path": "forli-cesena"}
    },
    {
      "path": "san-mauro-pascoli",
      "title": "San Mauro Pascoli",
      "province": {"label": "Forlì Cesena", "path": "forli-cesena"}
    },
    {
      "path": "santa-sofia",
      "title": "Santa Sofia",
      "province": {"label": "Forlì Cesena", "path": "forli-cesena"}
    },
    { "path": "sarsina", "title": "Sarsina", "province": {"label": "Forlì Cesena", "path": "forli-cesena"} },
    {
      "path": "savignano-sul-rubicone",
      "title": "Savignano sul Rubicone",
      "province": {"label": "Forlì Cesena", "path": "forli-cesena"}
    },
    {
      "path": "sogliano-al-rubicone",
      "title": "Sogliano al Rubicone",
      "province": {"label": "Forlì Cesena", "path": "forli-cesena"}
    },
    { "path": "tredozio", "title": "Tredozio", "province": {"label": "Forlì Cesena", "path": "forli-cesena"} },
    { "path": "verghereto", "title": "Verghereto", "province": {"label": "Forlì Cesena", "path": "forli-cesena"} },

    {
      "path": "abbadia-san-salvatore",
      "title": "Abbadia San Salvatore",
      "province": {"label": "Siena", "path": "siena"}
    },
    { "path": "asciano", "title": "Asciano", "province": {"label": "Siena", "path": "siena"} },
    { "path": "buonconvento", "title": "Buonconvento", "province": {"label": "Siena", "path": "siena"} },
    { "path": "casole-d-elsa", "title": "Casole d'Elsa", "province": {"label": "Siena", "path": "siena"} },
    {
      "path": "castellina-in-chianti",
      "title": "Castellina in Chianti",
      "province": {"label": "Siena", "path": "siena"}
    },
    {
      "path": "castelnuovo-berardenga",
      "title": "Castelnuovo Berardenga",
      "province": {"label": "Siena", "path": "siena"}
    },
    {
      "path": "castiglione-d-orcia",
      "title": "Castiglione d'Orcia",
      "province": {"label": "Siena", "path": "siena"}
    },
    { "path": "cetona", "title": "Cetona", "province": {"label": "Siena", "path": "siena"} },
    {
      "path": "chianciano-terme",
      "title": "Chianciano Terme",
      "province": {"label": "Siena", "path": "siena"}
    },
    { "path": "chiusdino", "title": "Chiusdino", "province": {"label": "Siena", "path": "siena"} },
    { "path": "chiusi", "title": "Chiusi", "province": {"label": "Siena", "path": "siena"} },
    {
      "path": "colle-di-val-d-elsa",
      "title": "Colle di Val d'Elsa",
      "province": {"label": "Siena", "path": "siena"}
    },
    {
      "path": "gaiole-in-chianti",
      "title": "Gaiole in Chianti",
      "province": {"label": "Siena", "path": "siena"}
    },
    { "path": "montalcino", "title": "Montalcino", "province": {"label": "Siena", "path": "siena"} },
    { "path": "montepulciano", "title": "Montepulciano", "province": {"label": "Siena", "path": "siena"} },
    { "path": "monteriggioni", "title": "Monteriggioni", "province": {"label": "Siena", "path": "siena"} },
    {
      "path": "monteroni-d-arbia",
      "title": "Monteroni d'Arbia",
      "province": {"label": "Siena", "path": "siena"}
    },
    { "path": "monticiano", "title": "Monticiano", "province": {"label": "Siena", "path": "siena"} },
    { "path": "murlo", "title": "Murlo", "province": {"label": "Siena", "path": "siena"} },
    {
      "path": "piancastagnaio",
      "title": "Piancastagnaio",
      "province": {"label": "Siena", "path": "siena"}
    },
    { "path": "pienza", "title": "Pienza", "province": {"label": "Siena", "path": "siena"} },
    { "path": "poggibonsi", "title": "Poggibonsi", "province": {"label": "Siena", "path": "siena"} },
    {
      "path": "radda-in-chianti",
      "title": "Radda in Chianti",
      "province": {"label": "Siena", "path": "siena"}
    },
    { "path": "radicofani", "title": "Radicofani", "province": {"label": "Siena", "path": "siena"} },
    { "path": "radicondoli", "title": "Radicondoli", "province": {"label": "Siena", "path": "siena"} },
    {
      "path": "rapolano-terme",
      "title": "Rapolano Terme",
      "province": {"label": "Siena", "path": "siena"}
    },
    {
      "path": "san-casciano-dei-bagni",
      "title": "San Casciano dei Bagni",
      "province": {"label": "Siena", "path": "siena"}
    },
    { "path": "san-gimignano", "title": "San Gimignano", "province": {"label": "Siena", "path": "siena"} },
    {
      "path": "san-quirico-d-orcia",
      "title": "San Quirico d'Orcia",
      "province": {"label": "Siena", "path": "siena"}
    },
    { "path": "sarteano", "title": "Sarteano", "province": {"label": "Siena", "path": "siena"} },
    { "path": "siena", "title": "Siena", "province": {"label": "Siena", "path": "siena"} },
    { "path": "sinalunga", "title": "Sinalunga", "province": {"label": "Siena", "path": "siena"} },
    { "path": "sovicille", "title": "Sovicille", "province": {"label": "Siena", "path": "siena"} },
    {
      "path": "torrita-di-siena",
      "title": "Torrita di Siena",
      "province": {"label": "Siena", "path": "siena"}
    },
    { "path": "trequanda", "title": "Trequanda", "province": {"label": "Siena", "path": "siena"} },

    { "path": "acquasparta", "title": "Acquasparta", "province": {"label": "Terni", "path": "terni"} },
    { "path": "allerona", "title": "Allerona", "province": {"label": "Terni", "path": "terni"} },
    { "path": "alviano", "title": "Alviano", "province": {"label": "Terni", "path": "terni"} },
    { "path": "amelia", "title": "Amelia", "province": {"label": "Terni", "path": "terni"} },
    { "path": "arrone", "title": "Arrone", "province": {"label": "Terni", "path": "terni"} },
    { "path": "attigliano", "title": "Attigliano", "province": {"label": "Terni", "path": "terni"} },
    {
      "path": "avigliano-umbro",
      "title": "Avigliano Umbro",
      "province": {"label": "Terni", "path": "terni"}
    },
    { "path": "baschi", "title": "Baschi", "province": {"label": "Terni", "path": "terni"} },
    {
      "path": "calvi-dell-umbria",
      "title": "Calvi dell'Umbria",
      "province": {"label": "Terni", "path": "terni"}
    },
    {
      "path": "castel-giorgio",
      "title": "Castel Giorgio",
      "province": {"label": "Terni", "path": "terni"}
    },
    {
      "path": "castel-viscardo",
      "title": "Castel Viscardo",
      "province": {"label": "Terni", "path": "terni"}
    },
    { "path": "fabro", "title": "Fabro", "province": {"label": "Terni", "path": "terni"} },
    { "path": "ferentillo", "title": "Ferentillo", "province": {"label": "Terni", "path": "terni"} },
    { "path": "ficulle", "title": "Ficulle", "province": {"label": "Terni", "path": "terni"} },
    { "path": "giove", "title": "Giove", "province": {"label": "Terni", "path": "terni"} },
    { "path": "guardea", "title": "Guardea", "province": {"label": "Terni", "path": "terni"} },
    {
      "path": "lugnano-in-teverina",
      "title": "Lugnano in Teverina",
      "province": {"label": "Terni", "path": "terni"}
    },
    {
      "path": "montecastrilli",
      "title": "Montecastrilli",
      "province": {"label": "Terni", "path": "terni"}
    },
    { "path": "montecchio", "title": "Montecchio", "province": {"label": "Terni", "path": "terni"} },
    { "path": "montefranco", "title": "Montefranco", "province": {"label": "Terni", "path": "terni"} },
    { "path": "montegabbione", "title": "Montegabbione", "province": {"label": "Terni", "path": "terni"} },
    {
      "path": "monteleone-d-orvieto",
      "title": "Monteleone d'Orvieto",
      "province": {"label": "Terni", "path": "terni"}
    },
    { "path": "narni", "title": "Narni", "province": {"label": "Terni", "path": "terni"} },
    { "path": "orvieto", "title": "Orvieto", "province": {"label": "Terni", "path": "terni"} },
    { "path": "otricoli", "title": "Otricoli", "province": {"label": "Terni", "path": "terni"} },
    { "path": "parrano", "title": "Parrano", "province": {"label": "Terni", "path": "terni"} },
    {
      "path": "penna-in-teverina",
      "title": "Penna in Teverina",
      "province": {"label": "Terni", "path": "terni"}
    },
    { "path": "polino", "title": "Polino", "province": {"label": "Terni", "path": "terni"} },
    { "path": "porano", "title": "Porano", "province": {"label": "Terni", "path": "terni"} },
    { "path": "san-gemini", "title": "San Gemini", "province": {"label": "Terni", "path": "terni"} },
    { "path": "san-venanzo", "title": "San Venanzo", "province": {"label": "Terni", "path": "terni"} },
    { "path": "stroncone", "title": "Stroncone", "province": {"label": "Terni", "path": "terni"} },
    { "path": "terni", "title": "Terni", "province": {"label": "Terni", "path": "terni"} }
  ]
}
